README.md
setup.cfg
setup.py
correios/__init__.py
correios/correios.py
py_correios.egg-info/PKG-INFO
py_correios.egg-info/SOURCES.txt
py_correios.egg-info/dependency_links.txt
py_correios.egg-info/not-zip-safe
py_correios.egg-info/requires.txt
py_correios.egg-info/top_level.txt