Metadata-Version: 1.0
Name: py-correios
Version: 0.0.1
Summary: Informações de CEP, encomendas e endereços em poucas linhas de código.
Home-page: https://github.com/hudsonbrendon/py-correios
Author: Hudson Brendon
Author-email: contato.hudsonbrendon@gmail.com
License: MIT
Platform: UNKNOWN
